issfile/__init__.py
issfile/_version.py
issfile-2023.2.0.dist-info/LICENSE
issfile-2023.2.0.dist-info/METADATA
issfile-2023.2.0.dist-info/WHEEL
issfile-2023.2.0.dist-info/entry_points.txt
issfile-2023.2.0.dist-info/top_level.txt
issfile-2023.2.0.dist-info/RECORD
