Metadata-Version: 2.1
Name: issfile
Version: 2023.2.0
Summary: Open ISS files.
Home-page: https://github.com/wimpomp/issfile
Author: Wim Pomp @ Lenstra lab NKI
Author-email: w.pomp@nki.nl
Classifier: Programming Language :: Python :: 3
Classifier: License :: OSI Approved :: GNU General Public License v3 (GPLv3)
Classifier: Operating System :: OS Independent
Requires-Python: >=3.8
License-File: LICENSE
Requires-Dist: numpy
Requires-Dist: matplotlib
Requires-Dist: tqdm
Requires-Dist: pyyaml
Requires-Dist: tiffwrite (>=2022.10.2)
